AUTHORS.rst
CONTRIBUTING.rst
HISTORY.rst
LICENSE
MANIFEST.in
README.rst
setup.cfg
setup.py
docs/Makefile
docs/authors.rst
docs/conf.py
docs/contributing.rst
docs/history.rst
docs/index.rst
docs/installation.rst
docs/make.bat
docs/readme.rst
docs/usage.rst
tests/__init__.py
tests/test_xsconnect.py
xsconnect/__init__.py
xsconnect/gxsconn.py
xsconnect/version.py
xsconnect/xess.gif
xsconnect/xsconn.py
xsconnect/xsconnect.py
xsconnect.egg-info/PKG-INFO
xsconnect.egg-info/SOURCES.txt
xsconnect.egg-info/dependency_links.txt
xsconnect.egg-info/entry_points.txt
xsconnect.egg-info/not-zip-safe
xsconnect.egg-info/pbr.json
xsconnect.egg-info/top_level.txt
xsconnect/daughterboards/CAT.py
xsconnect/daughterboards/XuLA.py
xsconnect/daughterboards/XuLA2.py
xsconnect/daughterboards/__init__.py
xsconnect/motherboards/CAT_Board_V0_2.py
xsconnect/motherboards/LogicPodMini_V1.py
xsconnect/motherboards/StickIt_V321.py
xsconnect/motherboards/StickIt_V4.py
xsconnect/motherboards/__init__.py
xsconnect/peripheralboards/Generic.py
xsconnect/peripheralboards/RPi_V2.py
xsconnect/peripheralboards/StickIt_AudioIO_V1.py
xsconnect/peripheralboards/StickIt_AudioIO_V2.py
xsconnect/peripheralboards/StickIt_Buttons_V2.py
xsconnect/peripheralboards/StickIt_DIPSwitch_V1.py
xsconnect/peripheralboards/StickIt_Grove.py
xsconnect/peripheralboards/StickIt_LEDDigits_V2.py
xsconnect/peripheralboards/StickIt_MPU_6050_V1.py
xsconnect/peripheralboards/StickIt_MPU_9150_V1.py
xsconnect/peripheralboards/StickIt_OctoADC_V1.py
xsconnect/peripheralboards/StickIt_PS2_V2.py
xsconnect/peripheralboards/StickIt_QuadDAC_V1.py
xsconnect/peripheralboards/StickIt_Rotary_Encoder_V1.py
xsconnect/peripheralboards/StickIt_Rotary_Encoder_V2.py
xsconnect/peripheralboards/StickIt_SmallButtons_V1.py
xsconnect/peripheralboards/StickIt_VGA_V1.py
xsconnect/peripheralboards/__init__.py