Metadata-Version: 1.1
Name: xsconnect
Version: 0.1.4
Summary: Generate pin assignment constraints for a given combination of XESS peripheral + motherboard + daughterboard.
Home-page: https://github.com/xesscorp/xsconnect
Author: XESS Corporation
Author-email: info@xess.com
License: MIT
Keywords: xsconnect
Platform: UNKNOWN
Classifier: Development Status :: 2 - Pre-Alpha
Classifier: Intended Audience :: Developers
Classifier: License :: OSI Approved :: MIT License
Classifier: Natural Language :: English
Classifier: Programming Language :: Python :: 2
Classifier: Programming Language :: Python :: 2.6
Classifier: Programming Language :: Python :: 2.7
